mockaioredis/__init__.py
mockaioredis/pool.py
mockaioredis/util.py
mockaioredis/commands/__init__.py
mockaioredis/commands/generic.py
mockaioredis/commands/hash.py
mockaioredis/commands/list.py
mockaioredis/commands/set.py
mockaioredis-0.0.16.dist-info/LICENSE
mockaioredis-0.0.16.dist-info/METADATA
mockaioredis-0.0.16.dist-info/WHEEL
mockaioredis-0.0.16.dist-info/top_level.txt
mockaioredis-0.0.16.dist-info/RECORD
