Metadata-Version: 2.1
Name: mockaioredis
Version: 0.0.16
Summary: Mock implementation of aioredis
Home-page: https://github.com/kblin/mockaioredis
Author: Kai Blin
Author-email: kblin@biosustain.dtu.dk
License: Apache Software License
Platform: POSIX
Classifier: License :: OSI Approved :: Apache Software License
Classifier: Development Status :: 3 - Alpha
Classifier: Programming Language :: Python
Classifier: Programming Language :: Python :: 3
Classifier: Programming Language :: Python :: 3.5
Classifier: Operating System :: POSIX
Classifier: Environment :: Web Environment
Classifier: Intended Audience :: Developers
Classifier: Topic :: Software Development
Classifier: Topic :: Software Development :: Libraries
Requires-Dist: aioredis
Requires-Dist: mockredispy-kblin (>=2.9.3.3)
Provides-Extra: shipping
Requires-Dist: twine ; extra == 'shipping'
Provides-Extra: testing
Requires-Dist: coverage ; extra == 'testing'
Requires-Dist: pytest ; extra == 'testing'
Requires-Dist: pytest-asyncio ; extra == 'testing'
Requires-Dist: pytest-cov ; extra == 'testing'
